abstractcore/__init__.py
abstractcore/download.py
abstractcore/apps/__init__.py
abstractcore/apps/__main__.py
abstractcore/apps/app_config_utils.py
abstractcore/apps/deepsearch.py
abstractcore/apps/extractor.py
abstractcore/apps/intent.py
abstractcore/apps/judge.py
abstractcore/apps/summarizer.py
abstractcore/architectures/__init__.py
abstractcore/architectures/detection.py
abstractcore/architectures/enums.py
abstractcore/assets/architecture_formats.json
abstractcore/assets/model_capabilities.json
abstractcore/assets/session_schema.json
abstractcore/compression/__init__.py
abstractcore/compression/analytics.py
abstractcore/compression/cache.py
abstractcore/compression/config.py
abstractcore/compression/exceptions.py
abstractcore/compression/glyph_processor.py
abstractcore/compression/optimizer.py
abstractcore/compression/orchestrator.py
abstractcore/compression/pil_text_renderer.py
abstractcore/compression/quality.py
abstractcore/compression/text_formatter.py
abstractcore/compression/vision_compressor.py
abstractcore/config/__init__.py
abstractcore/config/main.py
abstractcore/config/manager.py
abstractcore/config/vision_config.py
abstractcore/core/__init__.py
abstractcore/core/enums.py
abstractcore/core/factory.py
abstractcore/core/interface.py
abstractcore/core/retry.py
abstractcore/core/session.py
abstractcore/core/types.py
abstractcore/embeddings/__init__.py
abstractcore/embeddings/manager.py
abstractcore/embeddings/models.py
abstractcore/events/__init__.py
abstractcore/exceptions/__init__.py
abstractcore/mcp/__init__.py
abstractcore/mcp/client.py
abstractcore/mcp/factory.py
abstractcore/mcp/naming.py
abstractcore/mcp/stdio_client.py
abstractcore/mcp/tool_source.py
abstractcore/media/__init__.py
abstractcore/media/auto_handler.py
abstractcore/media/base.py
abstractcore/media/capabilities.py
abstractcore/media/types.py
abstractcore/media/vision_fallback.py
abstractcore/media/handlers/__init__.py
abstractcore/media/handlers/anthropic_handler.py
abstractcore-2.9.1.dist-info/licenses/LICENSE
abstractcore-2.9.1.dist-info/METADATA
abstractcore-2.9.1.dist-info/WHEEL
abstractcore-2.9.1.dist-info/entry_points.txt
abstractcore-2.9.1.dist-info/top_level.txt
abstractcore-2.9.1.dist-info/RECORD
