Metadata-Version: 2.4
Name: abstractcore
Version: 2.9.1
Summary: Unified interface to all LLM providers with essential infrastructure for tool calling, streaming, and model management
Author-email: Laurent-Philippe Albou <contact@abstractcore.ai>
Maintainer-email: Laurent-Philippe Albou <contact@abstractcore.ai>
License: MIT
Project-URL: Homepage, https://lpalbou.github.io/AbstractCore
Project-URL: Documentation, https://github.com/lpalbou/AbstractCore#readme
Project-URL: Repository, https://github.com/lpalbou/AbstractCore
Project-URL: Bug Tracker, https://github.com/lpalbou/AbstractCore/issues
Project-URL: Changelog, https://github.com/lpalbou/AbstractCore/blob/main/CHANGELOG.md
Keywords: llm,openai,anthropic,ollama,lmstudio,huggingface,mlx,ai,machine-learning,natural-language-processing,tool-calling,streaming
Classifier: Development Status :: 4 - Beta
Classifier: Intended Audience :: Developers
Classifier: License :: OSI Approved :: MIT License
Classifier: Operating System :: OS Independent
Classifier: Programming Language :: Python :: 3
Classifier: Programming Language :: Python :: 3.9
Classifier: Programming Language :: Python :: 3.10
Classifier: Programming Language :: Python :: 3.11
Classifier: Programming Language :: Python :: 3.12
Classifier: Topic :: Software Development :: Libraries :: Python Modules
Classifier: Topic :: Scientific/Engineering :: Artificial Intelligence
Classifier: Topic :: Internet :: WWW/HTTP :: HTTP Servers
Requires-Python: >=3.9
License-File: LICENSE
Requires-Dist: pydantic<3.0.0,>=2.0.0
Requires-Dist: httpx<1.0.0,>=0.24.0
Requires-Dist: tiktoken<1.0.0,>=0.5.0
Requires-Dist: requests<3.0.0,>=2.25.0
Requires-Dist: beautifulsoup4<5.0.0,>=4.12.0
Requires-Dist: Pillow<12.0.0,>=10.0.0
Provides-Extra: openai
Requires-Dist: openai<2.0.0,>=1.0.0; extra == "openai"
Provides-Extra: anthropic
Requires-Dist: anthropic<1.0.0,>=0.25.0; extra == "anthropic"
Provides-Extra: ollama
Provides-Extra: lmstudio
Provides-Extra: huggingface
Requires-Dist: transformers<5.0.0,>=4.57.1; extra == "huggingface"
Requires-Dist: torch<3.0.0,>=2.6.0; extra == "huggingface"
Requires-Dist: torchvision>=0.17.0; extra == "huggingface"
Requires-Dist: torchaudio>=2.1.0; extra == "huggingface"
Requires-Dist: llama-cpp-python<1.0.0,>=0.2.0; extra == "huggingface"
Requires-Dist: outlines>=0.1.0; extra == "huggingface"
Provides-Extra: mlx
Requires-Dist: mlx<1.0.0,>=0.15.0; extra == "mlx"
Requires-Dist: mlx-lm<1.0.0,>=0.15.0; extra == "mlx"
Requires-Dist: outlines>=0.1.0; extra == "mlx"
Provides-Extra: vllm
Requires-Dist: vllm<1.0.0,>=0.6.0; extra == "vllm"
Provides-Extra: embeddings
Requires-Dist: sentence-transformers<6.0.0,>=5.1.0; extra == "embeddings"
Requires-Dist: numpy<2.0.0,>=1.20.0; extra == "embeddings"
Provides-Extra: processing
Provides-Extra: tools
Requires-Dist: beautifulsoup4<5.0.0,>=4.12.0; extra == "tools"
Requires-Dist: lxml<6.0.0,>=4.9.0; extra == "tools"
Requires-Dist: ddgs<10.0.0,>=9.10.0; python_version >= "3.10" and extra == "tools"
Requires-Dist: duckduckgo-search<4.0.0,>=3.8.0; python_version < "3.10" and extra == "tools"
Requires-Dist: psutil<6.0.0,>=5.9.0; extra == "tools"
Provides-Extra: tool
Requires-Dist: beautifulsoup4<5.0.0,>=4.12.0; extra == "tool"
Requires-Dist: lxml<6.0.0,>=4.9.0; extra == "tool"
Requires-Dist: ddgs<10.0.0,>=9.10.0; python_version >= "3.10" and extra == "tool"
Requires-Dist: duckduckgo-search<4.0.0,>=3.8.0; python_version < "3.10" and extra == "tool"
Requires-Dist: psutil<6.0.0,>=5.9.0; extra == "tool"
Provides-Extra: media
Requires-Dist: Pillow<12.0.0,>=10.0.0; extra == "media"
Requires-Dist: pymupdf4llm<1.0.0,>=0.0.20; extra == "media"
Requires-Dist: unstructured[office]<1.0.0,>=0.10.0; extra == "media"
Requires-Dist: pandas<3.0.0,>=1.0.0; extra == "media"
Provides-Extra: compression
Requires-Dist: abstractcore[media]; extra == "compression"
Requires-Dist: pdf2image<2.0.0,>=1.16.0; extra == "compression"
Provides-Extra: api-providers
Requires-Dist: abstractcore[anthropic,openai]; extra == "api-providers"
Provides-Extra: local-providers
Requires-Dist: abstractcore[lmstudio,mlx,ollama]; extra == "local-providers"
Provides-Extra: local-providers-apple
Requires-Dist: abstractcore[lmstudio,mlx,ollama]; extra == "local-providers-apple"
Provides-Extra: local-providers-gpu
Requires-Dist: abstractcore[lmstudio,ollama,vllm]; extra == "local-providers-gpu"
Provides-Extra: gpu-providers
Requires-Dist: abstractcore[huggingface,vllm]; extra == "gpu-providers"
Provides-Extra: heavy-providers
Requires-Dist: abstractcore[huggingface]; extra == "heavy-providers"
Provides-Extra: all-providers
Requires-Dist: abstractcore[anthropic,embeddings,huggingface,lmstudio,mlx,ollama,openai,vllm]; extra == "all-providers"
Provides-Extra: all-providers-apple
Requires-Dist: abstractcore[anthropic,embeddings,huggingface,lmstudio,mlx,ollama,openai]; extra == "all-providers-apple"
Provides-Extra: all-providers-gpu
Requires-Dist: abstractcore[anthropic,embeddings,huggingface,lmstudio,ollama,openai,vllm]; extra == "all-providers-gpu"
Provides-Extra: all-providers-non-mlx
Requires-Dist: abstractcore[anthropic,embeddings,huggingface,lmstudio,ollama,openai]; extra == "all-providers-non-mlx"
Provides-Extra: local-providers-non-mlx
Requires-Dist: abstractcore[lmstudio,ollama]; extra == "local-providers-non-mlx"
Provides-Extra: all
Requires-Dist: abstractcore[anthropic,compression,dev,docs,embeddings,huggingface,lmstudio,media,mlx,ollama,openai,processing,server,test,tools,vllm]; extra == "all"
Provides-Extra: all-apple
Requires-Dist: abstractcore[anthropic,compression,dev,docs,embeddings,huggingface,lmstudio,media,mlx,ollama,openai,processing,server,test,tools]; extra == "all-apple"
Provides-Extra: all-gpu
Requires-Dist: abstractcore[anthropic,compression,dev,docs,embeddings,huggingface,lmstudio,media,ollama,openai,processing,server,test,tools,vllm]; extra == "all-gpu"
Provides-Extra: all-non-mlx
Requires-Dist: abstractcore[anthropic,compression,dev,docs,embeddings,huggingface,lmstudio,media,ollama,openai,processing,server,test,tools]; extra == "all-non-mlx"
Provides-Extra: lightweight
Requires-Dist: abstractcore[anthropic,compression,embeddings,lmstudio,media,ollama,openai,processing,server,tools]; extra == "lightweight"
Provides-Extra: dev
Requires-Dist: pytest>=7.0.0; extra == "dev"
Requires-Dist: pytest-asyncio>=0.21.0; extra == "dev"
Requires-Dist: pytest-mock>=3.10.0; extra == "dev"
Requires-Dist: black>=23.0.0; extra == "dev"
Requires-Dist: isort>=5.12.0; extra == "dev"
Requires-Dist: mypy>=1.5.0; extra == "dev"
Requires-Dist: ruff>=0.1.0; extra == "dev"
Requires-Dist: pre-commit>=3.0.0; extra == "dev"
Provides-Extra: server
Requires-Dist: fastapi<1.0.0,>=0.100.0; extra == "server"
Requires-Dist: uvicorn[standard]<1.0.0,>=0.23.0; extra == "server"
Requires-Dist: sse-starlette<2.0.0,>=1.6.0; extra == "server"
Provides-Extra: test
Requires-Dist: pytest>=7.0.0; extra == "test"
Requires-Dist: pytest-asyncio>=0.21.0; extra == "test"
Requires-Dist: pytest-mock>=3.10.0; extra == "test"
Requires-Dist: pytest-cov>=4.0.0; extra == "test"
Requires-Dist: responses>=0.23.0; extra == "test"
Requires-Dist: httpx>=0.24.0; extra == "test"
Provides-Extra: docs
Requires-Dist: mkdocs>=1.5.0; extra == "docs"
Requires-Dist: mkdocs-material>=9.0.0; extra == "docs"
Requires-Dist: mkdocstrings[python]>=0.22.0; extra == "docs"
Requires-Dist: mkdocs-autorefs>=0.4.0; extra == "docs"
Provides-Extra: full-dev
Requires-Dist: abstractcore[all-providers,dev,docs,test,tools]; extra == "full-dev"
Dynamic: license-file
